odoo9_addon_event_email_reminder-9.0.1.1.1-py2.7-nspkg.pth
odoo9_addon_event_email_reminder-9.0.1.1.1.dist-info/DESCRIPTION.rst
odoo9_addon_event_email_reminder-9.0.1.1.1.dist-info/METADATA
odoo9_addon_event_email_reminder-9.0.1.1.1.dist-info/RECORD
odoo9_addon_event_email_reminder-9.0.1.1.1.dist-info/WHEEL
odoo9_addon_event_email_reminder-9.0.1.1.1.dist-info/metadata.json
odoo9_addon_event_email_reminder-9.0.1.1.1.dist-info/namespace_packages.txt
odoo9_addon_event_email_reminder-9.0.1.1.1.dist-info/top_level.txt
odoo_addons/event_email_reminder/README.rst
odoo_addons/event_email_reminder/__init__.py
odoo_addons/event_email_reminder/__openerp__.py
odoo_addons/event_email_reminder/data/event_email_reminder_data.xml
odoo_addons/event_email_reminder/i18n/es.po
odoo_addons/event_email_reminder/models/__init__.py
odoo_addons/event_email_reminder/models/event.py
odoo_addons/event_email_reminder/static/description/icon.png
odoo_addons/event_email_reminder/tests/__init__.py
odoo_addons/event_email_reminder/tests/test_event_event.py
